Metadata-Version: 1.0
Name: distributions-kris
Version: 0.1
Summary: Gaussian distributions
Home-page: UNKNOWN
Author: Kris
Author-email: example@example.com
License: UNKNOWN
Platform: UNKNOWN
